{
	"$schema": "https://biomejs.dev/schemas/1.9.4/schema.json",
	"organizeImports": {
		"enabled": true
	},
	"linter": {
		"enabled": true,
		"rules": {
			"security": {
				"noDangerouslySetInnerHtml": "off"
			},
			"suspicious": {
				"noExplicitAny": "off",
				"noArrayIndexKey": "off",
				"noImplicitAnyLet": "off",
				"noMisleadingCharacterClass": "off",
				"noControlCharactersInRegex": "off"
			},
			"a11y": {
				"noSvgWithoutTitle": "off",
				"useButtonType": "off",
				"useKeyWithClickEvents": "off",
				"noLabelWithoutControl": "off",
				"useValidAriaRole": "off"
			},
			"style": {
				"noNonNullAssertion": "off",
				"noUnusedTemplateLiteral": "off",
				"useImportType": "off",
				"noVar": "off",
				"noArguments": "off",
				"noUselessElse": "off"
			},
			"correctness": {
				"useExhaustiveDependencies": "off",
				"noInnerDeclarations": "off"
			},
			"complexity": {
				"noForEach": "off"
			}
		}
	},
	"json": {
		"parser": {
			"allowComments": true
		}
	},
	"files": {
		"ignore": ["**/node_modules/**", "**/dist/**", "**/build/**", "**/.next/**"]
	}
}
